dsdlab-main/210905294_B/Week9/q1/q1.v

module q1(input [3:0] W, input En,output f);
	wire [0:15] Y;
	dec4to16 decoder(W, En, Y);
	assign f=Y[1] | Y[3] | Y[6] | Y[7] | Y[9] | Y[14] | Y[15];
endmodule

module dec4to16 (input [3:0] W, input En, output [0:15] Y);
	wire t1, t2;
    assign t1 = ~W[3] & En;
    assign t2 = W[3] & En;
	dec3to8 stage0(W[2:0], Y[0:7], t1);
    dec3to8 stage1(W[2:0], Y[8:15], t2);
endmodule

module dec3to8 (W, Y, En);
	input [2:0] W;
	input En;
	output [0:7] Y;
	reg [0:7] Y;
	always @(W or En)
	begin
		if (En == 0)
			Y = 8'b00000000;
		else
			case (W)
				0: Y = 8'b10000000;
				1: Y = 8'b01000000;
				2: Y = 8'b00100000;
				3: Y = 8'b00010000;
				4: Y = 8'b00001000;
				5: Y = 8'b00000100;
				6: Y = 8'b00000010;
				7: Y = 8'b00000001;
			endcase
	end
endmodule

dsdlab-main/210905294_B/Week9/q1/q1_tb.v
`timescale 1ns/1ns
`include "q1.v"

module q1_tb();
reg [3:0] w;
reg En;
wire f;

q1 q(w,En,f);
initial
begin
    $dumpfile("q1_tb.vcd");
    $dumpvars(0,q1_tb);

    w = 0; En = 1; #20;
    w = 1; En = 1; #20;
    w = 2; En = 1; #20;
    w = 3; En = 1; #20;

    $display("Test Complete");

end
endmodule

dsdlab-main/210905294_B/Week9/q1/q1_tb.vcd
$date
	Thu Oct 27 09:59:03 2022
$end
$version
	Icarus Verilog
$end
$timescale
	1ns
$end
$scope module q1_tb $end
$var wire 1 ! f $end
$var reg 1 " En $end
$var reg 4 # w [3:0] $end
$scope module q $end
$var wire 1 " En $end
$var wire 4 $ W [3:0] $end
$var wire 1 ! f $end
$var wire 16 % Y [0:15] $end
$scope module decoder $end
$var wire 1 " En $end
$var wire 4 & W [3:0] $end
$var wire 1 ' t1 $end
$var wire 1 ( t2 $end
$var wire 16 ) Y [0:15] $end
$scope module stage0 $end
$var wire 1 ' En $end
$var wire 3 * W [2:0] $end
$var reg 8 + Y [0:7] $end
$upscope $end
$scope module stage1 $end
$var wire 1 ( En $end
$var wire 3 , W [2:0] $end
$var reg 8 - Y [0:7] $end
$upscope $end
$upscope $end
$upscope $end
$upscope $end
$enddefinitions $end
#0
$dumpvars
b0 -
b0 ,
b10000000 +
b0 *
b1000000000000000 )
0(
1'
b0 &
b1000000000000000 %
b0 $
b0 #
1"
0!
$end
#20
1!
b100000000000000 %
b100000000000000 )
b1000000 +
b1 *
b1 ,
b1 #
b1 $
b1 &
#40
0!
b10000000000000 %
b10000000000000 )
b100000 +
b10 *
b10 ,
b10 #
b10 $
b10 &
#60
1!
b1000000000000 %
b1000000000000 )
b10000 +
b11 *
b11 ,
b11 #
b11 $
b11 &
#80
0!
b100000000000 %
b100000000000 )
b1000 +
b100 *
b100 ,
b100 #
b100 $
b100 &
#100
b10000000000 %
b10000000000 )
b100 +
b101 *
b101 ,
b101 #
b101 $
b101 &
#120
1!
b1000000000 %
b1000000000 )
b10 +
b110 *
b110 ,
b110 #
b110 $
b110 &
#140
b100000000 %
b100000000 )
b1 +
b111 *
b111 ,
b111 #
b111 $
b111 &
