dsdlab-main/210905294_B/Week3/ques4/struct.v
module struct(a,b,c,d,f);
input a,b,c,d;
output f;

assign f = ~((~d)|((~c)&(~a)));

endmodule

dsdlab-main/210905294_B/Week3/ques2/struct_tb.v
`timescale 1ns/1ns
`include "struct.v"

module struct_tb;
reg a,b,c,d;
wire f;

struct uut(a,b,c,d,f);
initial begin

	$dumpfile("struct_tb.vcd");
	$dumpvars(0,struct_tb);

	a=0;b=0;c=0;d=0;
	#10;
	a=0;b=1;c=0;d=0;
	#10;
	a=0;b=0;c=1;d=0;
	#10;
	a=0;b=0;c=0;d=1;
	#10;
	a=1;b=0;c=0;d=0;
	#10;
	a=1;b=1;c=0;d=0;
	#10;
	a=1;b=0;c=1;d=0;
	#10;
	a=1;b=0;c=0;d=1;
	#10;
	a=0;b=0;c=1;d=1;
	#10;
	a=0;b=1;c=0;d=1;
	#10;
	a=0;b=1;c=1;d=0;
	#10;
	a=1;b=1;c=1;d=0;
	#10;
	a=1;b=1;c=0;d=1;
	#10;
	a=1;b=0;c=1;d=1;
	#10;
	a=0;b=1;c=1;d=1;
	#10;
	a=1;b=1;c=1;d=1;
	#10;

	$display("Test Complete");

end


endmodule

dsdlab-main/210905294_B/Week3/ques4/struct_tb.vcd
$date
	Thu Sep  8 16:10:42 2022
$end
$version
	Icarus Verilog
$end
$timescale
	1ns
$end
$scope module struct_tb $end
$var wire 1 ! f $end
$var reg 1 " a $end
$var reg 1 # b $end
$var reg 1 $ c $end
$var reg 1 % d $end
$scope module uut $end
$var wire 1 " a $end
$var wire 1 # b $end
$var wire 1 $ c $end
$var wire 1 % d $end
$var wire 1 ! f $end
$upscope $end
$upscope $end
$enddefinitions $end
#0
$dumpvars
0%
0$
0#
0"
0!
$end
#10
1#
#20
1$
0#
#30
1%
0$
#40
0%
1"
#50
1#
#60
1$
0#
#70
1!
1%
0$
#80
1$
0"
#90
0!
0$
1#
#100
0%
1$
#110
1"
#120
1!
1%
0$
#130
1$
0#
#140
1#
0"
#150
1"
