dsdlab-main/210905294_B/Week9/q3/q3.v
module q3(w, En, f);
    input [2:0] w;
    input En;
    output f;
    wire [0:7] y;

    dec decoder(w, En, y);
    assign f = y[3] | y[5] | y[6];
endmodule

module dec(w, En, y);
    input [2:0] w;
    input En;
    output [0:7] y;

    wire t1,t2;
    assign t1 = ~w[2] & En;
    assign t2 = w[2] & En;

    ttfd stage0(w[1:0],t1,y[0:3]);
    ttfd stage1(w[1:0],t2,y[4:7]);
endmodule

module ttfd(w,En,y);
    input [1:0] w;
    input En;
    output reg [0:3] y;
    always @(w or En)
    begin
            y=4'b0000;
        if (En == 1)
        begin
            case(w)
            0:  y[0] = 1;
            1:  y[1] = 1;
            2:  y[2] = 1;
            3:  y[3] = 1; 
            endcase
        end
    end
endmodule

dsdlab-main/210905294_B/Week9/q3/q3_tb.v
`timescale 1ns/1ns
`include "q3.v"

module q3_tb();
reg [2:0] w;
reg En;
wire f;

q3 q(w,En,f);
initial
begin
    $dumpfile("q3_tb.vcd");
    $dumpvars(0,q3_tb);

    w = 3'b000; En = 1; #20;
    w = 3'b001; En = 1; #20;
    w = 3'b010; En = 1; #20;
	w = 3'b011; En = 1; #20;
	w = 3'b100; En = 1; #20;
	w = 3'b101; En = 1; #20;
	w = 3'b110; En = 1; #20;
	w = 3'b111; En = 1; #20;

    $display("Test Complete");

end
endmodule

dsdlab-main/210905294_B/Week9/q3/q3_tb.vcd
$date
	Thu Oct 27 10:28:16 2022
$end
$version
	Icarus Verilog
$end
$timescale
	1ns
$end
$scope module q3_tb $end
$var wire 1 ! f $end
$var reg 1 " En $end
$var reg 3 # w [2:0] $end
$scope module q $end
$var wire 1 " En $end
$var wire 1 ! f $end
$var wire 3 $ w [2:0] $end
$var wire 8 % y [0:7] $end
$scope module decoder $end
$var wire 1 " En $end
$var wire 1 & t1 $end
$var wire 1 ' t2 $end
$var wire 3 ( w [2:0] $end
$var wire 8 ) y [0:7] $end
$scope module stage0 $end
$var wire 1 & En $end
$var wire 2 * w [1:0] $end
$var reg 4 + y [0:3] $end
$upscope $end
$scope module stage1 $end
$var wire 1 ' En $end
$var wire 2 , w [1:0] $end
$var reg 4 - y [0:3] $end
$upscope $end
$upscope $end
$upscope $end
$upscope $end
$enddefinitions $end
#0
$dumpvars
b0 -
b0 ,
b1000 +
b0 *
b10000000 )
b0 (
0'
1&
b10000000 %
b0 $
b0 #
1"
0!
$end
#20
b1000000 %
b1000000 )
b100 +
b1 *
b1 ,
b1 #
b1 $
b1 (
#40
b100000 %
b100000 )
b10 +
b10 *
b10 ,
b10 #
b10 $
b10 (
#60
1!
b10000 %
b10000 )
b1 +
b11 *
b11 ,
b11 #
b11 $
b11 (
#80
0!
0&
b1000 -
1'
b1000 %
b1000 )
b0 +
b0 *
b0 ,
b100 #
b100 $
b100 (
#100
1!
b100 %
b100 )
b100 -
b1 *
b1 ,
b101 #
b101 $
b101 (
#120
b10 %
b10 )
b10 -
b10 *
b10 ,
b110 #
b110 $
b110 (
#140
0!
b1 %
b1 )
b1 -
b11 *
b11 ,
b111 #
b111 $
b111 (
