dsdlab-main/Week4/ques1/decomposedFA.v
module decomposedFA(a,b,cin,s,cout);
	input a,b,cin;
	output s,cout;
	ha stage0(a,b,s1,c1);
	ha stage1(s1,cin,s,c2);
	or (cout,c1,c2);
endmodule

module ha(a,b,s,cout);
	input a,b;
	output s,cout;
	assign s = a ^ b;
	assign cout = a & b;
endmodule

dsdlab-main/210905294_B/Week4/ques1/decomposedFA_tb.v

`timescale 1ns/1ns
`include "decomposedFA.v"

module decomposedFA_tb;
reg a,b,cin;
wire s,cout;

decomposedFA dfa(a,b,cin,s,cout);
initial begin

	$dumpfile("decomposedFA_tb.vcd");
	$dumpvars(0,decomposedFA_tb);
	
	a=0;b=0;cin=0;#20;
	a=0;b=0;cin=1;#20;
	a=0;b=1;cin=0;#20;
	a=0;b=1;cin=1;#20;
	a=1;b=0;cin=0;#20;
	a=1;b=0;cin=1;#20;
	a=1;b=1;cin=0;#20;
	a=1;b=1;cin=1;#20;
	
	$display("Test Complete");
	
end 
endmodule

dsdlab-main/210905294_B/Week4/ques1/decomposedFA_tb.vcd
$date
	Thu Sep 15 15:00:41 2022
$end
$version
	Icarus Verilog
$end
$timescale
	1ns
$end
$scope module decomposedFA_tb $end
$var wire 1 ! s $end
$var wire 1 " cout $end
$var reg 1 # a $end
$var reg 1 $ b $end
$var reg 1 % cin $end
$scope module dfa $end
$var wire 1 # a $end
$var wire 1 $ b $end
$var wire 1 % cin $end
$var wire 1 " cout $end
$var wire 1 & s1 $end
$var wire 1 ! s $end
$var wire 1 ' c2 $end
$var wire 1 ( c1 $end
$scope module stage0 $end
$var wire 1 # a $end
$var wire 1 $ b $end
$var wire 1 ( cout $end
$var wire 1 & s $end
$upscope $end
$scope module stage1 $end
$var wire 1 & a $end
$var wire 1 % b $end
$var wire 1 ' cout $end
$var wire 1 ! s $end
$upscope $end
$upscope $end
$upscope $end
$enddefinitions $end
#0
$dumpvars
0(
0'
0&
0%
0$
0#
0"
0!
$end
#20
1!
1%
#40
1&
0%
1$
#60
1"
0!
1'
1%
#80
0"
1!
0'
0%
0$
1#
#100
1"
0!
1'
1%
#120
0'
0&
1(
0%
1$
#140
1!
1%
