dsdlab-main/210905294_B/lab_4/Q2/full_adder.v
module full_adder(a,b,c_in,s,c);
input a,b,c_in;
output s,c;
assign s = a^b^c_in;
assign c = (a&b)|(b&c_in)|(c_in&a);
endmodule

dsdlab-main/210905294_B/lab_4/Q1/full_adder_tb.v
`timescale 1ns/1ns
`include "full_adder.v"
module full_adder_tb;
reg a,b,c_in;
wire s,c;
full_adder uut(a,b,c_in,s,c);
initial
begin
$dumpfile("full_adder_tb.vcd");
$dumpvars(0,full_adder_tb);
c_in=0;
a=0;b=0;#20;
a=0;b=1;#20;
a=1;b=0;#20;
a=1;b=1;#20;
c_in=1;
a=0;b=0;#20;
a=0;b=1;#20;
a=1;b=0;#20;
a=1;b=1;#20;

$display("Test completed");
end
endmodule

dsdlab-main/210905294_B/lab_4/Q1/full_adder_tb.vcd
$date
	Thu Sep 15 14:38:49 2022
$end
$version
	Icarus Verilog
$end
$timescale
	1ns
$end
$scope module full_adder_tb $end
$var wire 1 ! s $end
$var wire 1 " c $end
$var reg 1 # a $end
$var reg 1 $ b $end
$var reg 1 % c_in $end
$scope module uut $end
$var wire 1 # a $end
$var wire 1 $ b $end
$var wire 1 " c $end
$var wire 1 % c_in $end
$var wire 1 ! s $end
$upscope $end
$upscope $end
$enddefinitions $end
#0
$dumpvars
0%
0$
0#
0"
0!
$end
#20
1!
1$
#40
0$
1#
#60
1"
0!
1$
#80
0"
1!
0$
0#
1%
#100
1"
0!
1$
#120
0$
1#
#140
1!
1$
